Audit_Alembic-0.2.0.dist-info/DESCRIPTION.rst
Audit_Alembic-0.2.0.dist-info/METADATA
Audit_Alembic-0.2.0.dist-info/RECORD
Audit_Alembic-0.2.0.dist-info/WHEEL
Audit_Alembic-0.2.0.dist-info/metadata.json
Audit_Alembic-0.2.0.dist-info/top_level.txt
audit_alembic/__init__.py
audit_alembic/__main__.py
audit_alembic/audit.py
audit_alembic/base.py
audit_alembic/cli.py
audit_alembic/exc.py
audit_alembic/util.py
