Metadata-Version: 2.0
Name: Audit-Alembic
Version: 0.2.0
Summary: An Alembic plugin to keep records of upgrades and downgrades.
Home-page: https://github.com/jpassaro/Audit-Alembic
Author: John Passaro
Author-email: john.a.passaro@gmail.com
License: BSD
Download-URL: https://github.com/jpassaro/Audit-Alembic/archive/0.2.0.tar.gz
Keywords: database,migration,db
Platform: UNKNOWN
Classifier: Development Status :: 2 - Pre-Alpha
Classifier: Intended Audience :: Developers
Classifier: License :: OSI Approved :: BSD License
Classifier: Operating System :: Unix
Classifier: Operating System :: POSIX
Classifier: Operating System :: Microsoft :: Windows
Classifier: Programming Language :: Python
Classifier: Programming Language :: Python :: 2.7
Classifier: Programming Language :: Python :: 3
Classifier: Programming Language :: Python :: 3.3
Classifier: Programming Language :: Python :: 3.4
Classifier: Programming Language :: Python :: 3.5
Classifier: Programming Language :: Python :: 3.6
Classifier: Programming Language :: Python :: Implementation :: CPython
Classifier: Programming Language :: Python :: Implementation :: PyPy
Classifier: Topic :: Utilities
Requires-Dist: alembic (>=0.9.4)
